
{
  "lang_name": "தமிழ்",
  "lang_code": "ta",
  "all_games": "அனைத்து விளையாட்டுக்கள்:",
  "find": "கண்டறி",
  "all_caps": "அனைத்து",
  "reimport": "மீண்டும் இறக்குமதி செய்க",
  "show_console": "கண்சோல் காட்டு",
  "create_subfolders": "உபதொகுப்புகள் உருவாக்கு",
  "file": "கோப்பு",
  "unpack_with": "இந்த உபகோப்புவையும் வெளிக்கவும்...",
  "compress_formats": "குறுக்கு வடிகட்டு",
  "find_formats": "வடிவங்கள் கண்டறி",
  "additional": "கூடுதல்",
  "consoles": "கன்சோல்கள்",
  "other": "மற்றவை",
  "archives": "கோப்புச்செலவுகள்",
  "game_engines": "விளையாட்டு எஞ்சின்கள்",
  "disk_images": "டிஸ்க் படங்கள்",
  "installers": "நிறுவுவிப்பளிக்குகள்",
  "convert": "மாற்று",
  "video": "காணொளி",
  "audio": "ஆடியோ",
  "textures": "அமைப்புகள்",
  "settings": "அமைப்புகள்",
  "themes": "தீம்கள்",
  "about": "பற்றி",
  "quick_open": "விரைவில் திற",
  "leave": "விடு",
  "language": "மொழி\\Language",
  "select_out_folder": "வெளியே கோப்புறையை தேர்ந்தெடு",
  "clear_out_folder": "வெளியே கோப்புறை அழிக்க",
  "make_out_folder": "வெளியே கோப்புறை உருவாக்கு",
  "delete_empty_files": "காலியாக கோப்புகளை நீக்கு",
  "delete_empty_subfolders": "காலியாக உபகோப்புகளை நீக்கு",
  "autofind": "தானியங்கி கண்டறி",
  "archive_scanner": "கோப்புச்செலவு கண்காணிப்பு",
  "file_list": "கோப்பு பட்டியல்",
  "create_theme": "தீம் உருவாக்கு",
  "select_something": "விளையாட்டு, நிருபவம் அல்லது கோப்பு வகையை தேர்ந்தெடு",
  "change_button": "பொத்தானை மாற்று",
  "cancel": "ரத்து செய்யுங்கள்",
  "delete_to_trash": "குப்பை கோப்பு",
  "full_delete": "முழுமையாக அழிக்கவும்",
  "show_on": "விளையாட்டில் பயன்படுத்தப்படும் எஞ்சின் காண்பி:",
  "by_name": "பெயர் மூலம்",
  "by_years": "ஆண்டுகள் மூலம்",
  "context_menu": "சூசி மெனு சரிபார்க்கவும்",
  "sort_by": "படிக்கடிகக்கு மூலம் வரிசைப்படுத்து:",
  "out_folder": "வெளிக்கோப்பு கோப்புறை",
  "apply": "பயன்படுத்து",
  "save_theme": "தீமை சேமி",
  "primary_color": "முதன்முதல் வண்ணம்",
  "primary_light": "முதன்முதல் வண்ணம்",
  "second_color": "இரண்டாவது வண்ணம்",
  "second_light": "இரண்டாவது வண்ணம்",
  "second_dark": "இரண்டாவது வண்ணம்",
  "font_color_1": "எழுத்து வண்ணம் 1",
  "font_color_2": "எழுத்து வண்ணம் 2",
  "enter_theme_name": "தீமின் பெயரை உள்ளிடவும்:"
}