
{
  "lang_name": "ไทย",
  "lang_code": "th",
  "all_games": "เกมทั้งหมด:",
  "find": "ค้นหา",
  "all_caps": "ทั้งหมด",
  "reimport": "นำเข้าอีกครั้ง",
  "show_console": "แสดงคอนโซล",
  "create_subfolders": "สร้างโฟลเดอร์ย่อยเพื่อ",
  "file": "ไฟล์",
  "unpack_with": "แตกไฟล์ด้วย...",
  "compress_formats": "รูปแบบบีบอัด",
  "find_formats": "ค้นหารูปแบบ",
  "additional": "เพิ่มเติม",
  "consoles": "เครื่องเล่นเกม",
  "other": "อื่นๆ",
  "archives": "แฟ้มเอกสาร",
  "game_engines": "เครื่องมือสำหรับเกม",
  "disk_images": "ภาพแผ่น",
  "installers": "ตัวติดตั้ง",
  "convert": "แปลง",
  "video": "วิดีโอ",
  "audio": "เสียง",
  "textures": "ลวดลาย",
  "settings": "การตั้งค่า",
  "themes": "ธีม",
  "about": "เกี่ยวกับโปรแกรม",
  "quick_open": "เปิดด่วน",
  "leave": "ออก",
  "language": "ภาษา\\Language",
  "select_out_folder": "เลือกโฟลเดอร์ออก",
  "clear_out_folder": "เคลียร์โฟลเดอร์ออก",
  "make_out_folder": "สร้างโฟลเดอร์ออก",
  "delete_empty_files": "ลบไฟล์ที่ว่างเปล่า",
  "delete_empty_subfolders": "ลบโฟลเดอร์ย่อยที่ว่างเปล่า",
  "autofind": "ค้นหาสคริปต์โดยอัตโนมัติ",
  "archive_scanner": "สแกนเนอร์แฟ้มเอกสาร",
  "file_list": "รายการไฟล์",
  "create_theme": "สร้างธีม",
  "select_something": "เลือกเกม โปรแกรม หรือประเภทไฟล์",
  "change_button": "เปลี่ยนปุ่ม",
  "cancel": "ยกเลิก",
  "delete_to_trash": "ลบไปที่ถังขยะ",
  "full_delete": "ลบทั้งหมด",
  "show_on": "แสดงเครื่องมือที่ใช้กับเกม:",
  "by_name": "ตามชื่อ",
  "by_years": "ตามปี",
  "context_menu": "ตรวจสอบในเมนูคอนเท็กซ์ต์",
  "sort_by": "เรียงตาม:",
  "out_folder": "โฟลเดอร์ออก",
  "apply": "ใช้",
  "save_theme": "บันทึกธีม",
  "primary_color": "สีหลัก",
  "primary_light": "สีหลัก (สว่าง)",
  "second_color": "สีที่สอง",
  "second_light": "สีที่สอง (สว่าง)",
  "second_dark": "สีที่สอง (เข้ม)",
  "font_color_1": "สีตัวอักษร 1",
  "font_color_2": "สีตัวอักษร 2",
  "enter_theme_name": "ป้อนชื่อธีม:"
}